{
  "project_info": {
    "project_number": "163430220369",
    "project_id": "movie-app-8d907",
    "storage_bucket": "movie-app-8d907.appspot.com"
  },
  "client": [
    {
      "client_info": {
        "mobilesdk_app_id": "1:163430220369:android:9bf565c7992317826a2e70",
        "android_client_info": {
          "package_name": "com.example.movie_app"
        }
      },
      "oauth_client": [
        {
          "client_id": "163430220369-ksnvukv9d0iactkf6htssm5tj2jgm9h1.apps.googleusercontent.com",
          "client_type": 1,
          "android_info": {
            "package_name": "com.example.movie_app",
            "certificate_hash": "b80a2a4476e88153110a19da538fd368f064eafb"
          }
        },
        {
          "client_id": "163430220369-2q1lcq0otjhjhgb6q77nnsgl34oacom5.apps.googleusercontent.com",
          "client_type": 3
        }
      ],
      "api_key": [
        {
          "current_key": "AIzaSyDaGPsQ5eY4ftrstLOfMtRju991R_jW38A"
        }
      ],
      "services": {
        "appinvite_service": {
          "other_platform_oauth_client": [
            {
              "client_id": "163430220369-2q1lcq0otjhjhgb6q77nnsgl34oacom5.apps.googleusercontent.com",
              "client_type": 3
            },
            {
              "client_id": "163430220369-d9k4q2u9lgqo1qm7llteirbcdmu8085o.apps.googleusercontent.com",
              "client_type": 2,
              "ios_info": {
                "bundle_id": "com.example.movieApp.RunnerTests"
              }
            }
          ]
        }
      }
    }
  ],
  "configuration_version": "1"
}